.gitignore
LICENSE
MANIFEST.in
README.TXT
setup.py
TIMEleSS/__init__.py
TIMEleSS/data/__init__.py
TIMEleSS/data/fcc_10bckg_.gff
TIMEleSS/data/gve-62-3.log
TIMEleSS/diffraction/ID27_hdf5_To_Edf.py
TIMEleSS/diffraction/__init__.py
TIMEleSS/diffraction/averageImage.py
TIMEleSS/diffraction/createEmptyImage.py
TIMEleSS/diffraction/dacShadowMask.py
TIMEleSS/diffraction/diamondSpotRemoval.py
TIMEleSS/diffraction/edf2tiffFileSeries.py
TIMEleSS/diffraction/edf2tiffSingle.py
TIMEleSS/diffraction/flatFieldFileSeries.py
TIMEleSS/diffraction/inpaint.py
TIMEleSS/diffraction/mccd2edf.py
TIMEleSS/diffraction/meanFileSeries.py
TIMEleSS/diffraction/subtractImage.py
TIMEleSS/diffraction/tiff2edf.py
TIMEleSS/evaluation/GSIndexingStatistics.py
TIMEleSS/evaluation/__init__.py
TIMEleSS/evaluation/extractEulerAngles.py
TIMEleSS/evaluation/extractGrainSizes.py
TIMEleSS/evaluation/fixGrainSpotterOutput.py
TIMEleSS/evaluation/relToAbsGrainSize.py
TIMEleSS/evaluation/removeUsedGVE.py
TIMEleSS/evaluation/testGSEulerAngles.py
TIMEleSS/evaluation/testGSvsGVE.py
TIMEleSS/evaluation/testGrainsPeaks.py
TIMEleSS/evaluation/testGrainsPeaksGui.py
TIMEleSS/evaluation/tthHistogram2Maud.py
TIMEleSS/evaluation/twoThetaHistFromGVE.py
TIMEleSS/general/__init__.py
TIMEleSS/general/cifTools.py
TIMEleSS/general/grain3DXRD.py
TIMEleSS/general/indexedPeak3DXRD.py
TIMEleSS/general/multigrainOutputParser.py
TIMEleSS/simulation/__init__.py
TIMEleSS/simulation/clearFLTGrains.py
TIMEleSS/simulation/clearGVEGrains.py
TIMEleSS/simulation/fltForGrains.py
TIMEleSS/simulation/grainComparison.py
TIMEleSS/simulation/grainPeaksComparison.py
TIMEleSS/simulation/grainSpotterMerge.py
TIMEleSS/simulation/printPeaksFromCIF.py
TIMEleSS/simulation/test.py
TIMEleSS/simulation/updateGVEFromCIF.py
TIMEleSS_tools.egg-info/PKG-INFO
TIMEleSS_tools.egg-info/SOURCES.txt
TIMEleSS_tools.egg-info/dependency_links.txt
TIMEleSS_tools.egg-info/entry_points.txt
TIMEleSS_tools.egg-info/requires.txt
TIMEleSS_tools.egg-info/top_level.txt